Metadata-Version: 2.4
Name: claude-usage-cli
Version: 1.1.2
Summary: Monitor Claude AI token usage with zero dependencies
Author-email: Claude Usage Monitor <noreply@example.com>
License-Expression: MIT
Project-URL: Homepage, https://github.com/your-username/claude-usage-monitor-cli
Project-URL: Repository, https://github.com/your-username/claude-usage-monitor-cli
Project-URL: Issues, https://github.com/your-username/claude-usage-monitor-cli/issues
Keywords: claude,api,usage,monitoring,cli,token
Classifier: Development Status :: 5 - Production/Stable
Classifier: Environment :: Console
Classifier: Intended Audience :: Developers
Classifier: Operating System :: OS Independent
Classifier: Programming Language :: Python :: 3
Classifier: Programming Language :: Python :: 3.7
Classifier: Programming Language :: Python :: 3.8
Classifier: Programming Language :: Python :: 3.9
Classifier: Programming Language :: Python :: 3.10
Classifier: Programming Language :: Python :: 3.11
Classifier: Programming Language :: Python :: 3.12
Classifier: Topic :: Software Development :: Libraries :: Python Modules
Classifier: Topic :: System :: Monitoring
Classifier: Topic :: Utilities
Requires-Python: >=3.9
